fancycmd/__init__.py
fancycmd/cmd.py
fancycmd/data_types.py
fancycmd/prompt.py
fancycmd-0.0.1.dist-info/DESCRIPTION.rst
fancycmd-0.0.1.dist-info/METADATA
fancycmd-0.0.1.dist-info/RECORD
fancycmd-0.0.1.dist-info/WHEEL
fancycmd-0.0.1.dist-info/metadata.json
fancycmd-0.0.1.dist-info/top_level.txt
