Metadata-Version: 2.0
Name: fancycmd
Version: 0.0.1
Summary: A fancy wrapper around readline
Home-page: https://github.com/anyms/fancycmd
Author: Jeeva
Author-email: hi@spidy.app
License: UNKNOWN
Keywords: cmd commandshell plugins
Platform: UNKNOWN
Classifier: Intended Audience :: Developers
Classifier: Intended Audience :: Education
Classifier: Intended Audience :: Science/Research
Classifier: Development Status :: 5 - Production/Stable
Classifier: Intended Audience :: Developers
Classifier: License :: OSI Approved :: MIT License
Classifier: Operating System :: MacOS :: MacOS X
Classifier: Operating System :: POSIX :: Linux
Classifier: Programming Language :: Python :: 3
Classifier: Topic :: Scientific/Engineering
Classifier: Topic :: System :: Clustering
Classifier: Topic :: System :: Distributed Computing
Classifier: Topic :: Software Development :: Libraries :: Python Modules
Classifier: Environment :: Console
